maven/__init__.py
maven/api/__init__.py
maven/api/endpoints/__init__.py
maven/api/endpoints/case.py
maven/api/main.py
maven/constants.py
maven/crud/__init__.py
maven/crud/create.py
maven/crud/read.py
maven/exceptions/__init__.py
maven/exceptions/exceptions.py
maven/maven_db/client_connection.py
maven/maven_db/config.py
maven/maven_db/maven_adapter.py
maven/models/__init__.py
maven/models/case.py
maven/models/pipeline.py
maven/models/pipeline_delivery_thresholds.py
maven/models/pipeline_qc_metrics.py
maven/models/sample.py
cg_maven-0.1.6.dist-info/METADATA
cg_maven-0.1.6.dist-info/WHEEL
cg_maven-0.1.6.dist-info/RECORD
